word4num/__init__.py
word4num/w4n_converter.py
word4num/dicts/10_en_words.json
word4num/dicts/11_en_words.json
word4num/dicts/12_en_words.json
word4num/dicts/13_en_words.json
word4num/dicts/14_en_words.json
word4num/dicts/15_en_words.json
word4num/dicts/16_en_words.json
word4num/dicts/17_en_words.json
word4num/dicts/18_en_words.json
word4num/dicts/19_en_words.json
word4num/dicts/21_en_words.json
word4num/dicts/22_en_words.json
word4num/dicts/3_en_words.json
word4num/dicts/4_en_words.json
word4num/dicts/5_en_words.json
word4num/dicts/6_en_words.json
word4num/dicts/7_en_words.json
word4num/dicts/8_en_words.json
word4num/dicts/9_en_words.json
word4num/dicts/__init__.py
word4num/dicts/all_en_words.json
word4num/dicts/dicts.py
word4num/letters/__init__.py
word4num/letters/letters.py
word4num-0.0.5.dist-info/METADATA
word4num-0.0.5.dist-info/WHEEL
word4num-0.0.5.dist-info/licenses/LICENSE
word4num-0.0.5.dist-info/RECORD
