Metadata-Version: 2.3
Name: word4num
Version: 0.0.5
Summary: Small library for encoding numbers to words and decoding it back.
Project-URL: Homepage, https://github.com/Nikdedov/word4num
Project-URL: Issues, https://github.com/Nikdedov/word4num/issues
Author-email: Nikdedov <nik.dedov@gmail.com>
License-File: LICENSE
Keywords: decode words,encode number,what3words,word number converter
Classifier: License :: OSI Approved :: MIT License
Classifier: Operating System :: OS Independent
Classifier: Programming Language :: Python :: 3
Requires-Python: >=3.9
